dagster_managed_elements/__init__.py
dagster_managed_elements/cli.py
dagster_managed_elements/py.typed
dagster_managed_elements/types.py
dagster_managed_elements/utils.py
dagster_managed_elements/version.py
dagster_managed_elements-0.28.13.dist-info/licenses/LICENSE
dagster_managed_elements-0.28.13.dist-info/METADATA
dagster_managed_elements-0.28.13.dist-info/WHEEL
dagster_managed_elements-0.28.13.dist-info/entry_points.txt
dagster_managed_elements-0.28.13.dist-info/top_level.txt
dagster_managed_elements-0.28.13.dist-info/RECORD
